aiowatttime/__init__.py
aiowatttime/client.py
aiowatttime/const.py
aiowatttime/emissions.py
aiowatttime/errors.py
aiowatttime/py.typed
aiowatttime-2024.6.0.dist-info/LICENSE
aiowatttime-2024.6.0.dist-info/METADATA
aiowatttime-2024.6.0.dist-info/WHEEL
aiowatttime-2024.6.0.dist-info/RECORD
