Metadata-Version: 2.1
Name: aiowatttime
Version: 2024.6.0
Summary: An asyncio-based Python3 library for interacting with WattTime
Home-page: https://github.com/bachya/aiowatttime
License: MIT
Author: Aaron Bach
Author-email: bachya1208@gmail.com
Requires-Python: >=3.10,<4.0
Classifier: License :: OSI Approved :: MIT License
Classifier: Programming Language :: Python
Classifier: Programming Language :: Python :: 3
Classifier: Programming Language :: Python :: 3.10
Classifier: Programming Language :: Python :: 3.11
Classifier: Programming Language :: Python :: 3.12
Classifier: Programming Language :: Python :: Implementation :: CPython
Classifier: Programming Language :: Python :: Implementation :: PyPy
Requires-Dist: aiohttp (>=3.9.0b0)
Requires-Dist: certifi (>=2023.07.22)
Requires-Dist: yarl (>=1.9.2)
Project-URL: Bug Tracker, https://github.com/bachya/aiowatttime/issues
Project-URL: Changelog, https://github.com/bachya/aiowatttime/releases
Project-URL: Repository, https://github.com/bachya/aiowatttime
